Metadata-Version: 2.1
Name: aimlprog
Version: 0.0.3
Summary: Programs
Home-page: UNKNOWN
Author: Shivam
Author-email: <shivamk438@gmail.com>
License: UNKNOWN
Keywords: python,program,VTU,AI&ML,SCE
Platform: UNKNOWN
Classifier: Development Status :: 1 - Planning
Classifier: Intended Audience :: Developers
Classifier: Programming Language :: Python :: 3
Classifier: Operating System :: Unix
Classifier: Operating System :: MacOS :: MacOS X
Classifier: Operating System :: Microsoft :: Windows
